matcho/__init__.py
matcho/bindings.py
matcho/exceptions.py
matcho/pattern.py
matcho/template.py
matcho-0.3.5.dist-info/LICENSE
matcho-0.3.5.dist-info/METADATA
matcho-0.3.5.dist-info/WHEEL
matcho-0.3.5.dist-info/top_level.txt
matcho-0.3.5.dist-info/RECORD
