Metadata-Version: 2.1
Name: matcho
Version: 0.3.5
Summary: A pattern matching and template library.
Home-page: https://github.com/mbillingr/matcho
Author: Martin Billinger-Finke
License: LICENSE
Platform: UNKNOWN
Requires-Python: >=3.7
License-File: LICENSE
